[{"title": "Apple em promoção: descontos em iPhones, Macbooks e airpods", "text": "produtos Apple sinônimo qualidade alto investimento celulares notebooks outros gadgets especificações avançadas marca desejo consumo usuários abrem mão qualidade modernidade quer iPhone chamar seu notebook potente trabalhar estudar jogar pode aproveitar promoções Semana Tech Amazon várias ofertas produtos Apple airpods iPhone 14 aproveite descontos garanta novo gadget Veja principais ofertas seguir Fone Ouvido Bluetooth Apple AirPods 2ª geração 17 OFF Fone Ouvido Bluetooth Apple AirPods 2ª geração fones fio populares mercado ajuste universal ativação automática produtos Apple bateria 5 horas R 114397 AMAZON R 94900 Fone Ouvido Bluetooth Apple 3ª geração 14 OFF Fone Ouvido Bluetooth Apple AirPods 3ª geração Áudio espacial escutar som todos lados equalização adaptativa ajusta música ouvidos bateria maior duração resistência suor água R 179900 AMAZON R 154900 Notebook Apple MacBook Air 13 Processador M1 8GB RAM SSD 256GB 40 OFF Notebook Apple MacBook Air 13 Processador M1 8GB RAM SSD 256GB MacBook Apple potente CPU 8core 35 vezes rápida altura projetos exigentes R 1299900 AMAZON R 779900 Notebook Apple MacBook Air 13 Chip M2 SSD 512G 24 OFF Notebook Apple MacBook Air 13 Chip M2 SSD 512GB Faça tudo rápido CPU 8 núcleos última geração GPU 10 núcleos 24 GB memória unificada R 1629900 AMAZON R 1244900 Smartphone Apple Apple iPhone 11 64GB 44 OFF Smartphone Apple iPhone 11 64GB iPhone 11 61 polegadas tela chip A13 Bionic desempenho remarcável câmera dupla tiram excelentes fotos vídeos bom investimento procura qualidade durabilidade R 499900 AMAZON R 279900 Smartphone Apple iPhone 12 128GB 43 OFF Smartphone Apple iPhone 12 128 GB Conta tela Super Retina XDR brilhante 61 polegadas Ceramic Shield quatro vezes resistente quedas Fotos surpreendentes pouca luz modo Noite todas câmeras R 699900 AMAZON R 399900 Smartphone Apple iPhone 13 128GB 38 OFF Smartphone Apple iPhone 13 128GB iPhone 13 tela superbrilhante projetada resistente sistema câmera dupla fotos vídeos qualidade cinema design pensado forte resistente água poeira R 759900 AMAZON R 469889 Smartphone Apple iPhone 14 256GB Smartphone Apple iPhone 14 256GB iPhone 14 possui tela 61 conectividade 5G câmera12MP resolução 2532 x 1170 pixels 460 ppi ideal fazer fotos alta qualidade Possui função detecção acidente maior duração bateria 20h reprodução vídeo TECMUNDO COMPARADOR R 619900  Conheça Comparador TecMundo Conheça Comparador TecMundo Dezenas categorias milhares produtos menores preços garantir melhores escolhas compras Clique conheça comparador preços CONHEÇA Comparador TecMundo possui milhares produtos categorias celulares Smart TVs notebooks casa inteligente consoles eletrodomésticos mais página encontrará produtos deseja poderá fazer comparação preço principais varejistas mercado Acesse site aproveite ofertas disponíveis", "link": "https://www.tecmundo.com.br/produto/264645-apple-promocao-descontos-em-iphones-macbooks-airpods.htm"}, {"title": "Comparativo: Galaxy Buds 2 Pro VS AirPods Pro de 2ª geração", "text": "muitas pessoas fones fio itens obrigatórios entretenimento ferramenta trabalho categoria premium dois modelos destacam AirPods Pro 2ª Geração Apple Galaxy Buds 2 Pro Samsung Ambos acessórios prometem entregar experiência topo linha consumidores Bem como cada produto apresenta certas particularidades podem chamar atenção determinados ouvintes dúvida sobre fone ouvido combina perfil TecMundo traz breve comparativo dois modelos Conheça principais pontos cada produto e final veja vencedor desta batalha AirPods Pro 2ª Geração Fone Ouvido Apple AirPods Pro 2ª Geração fone ouvido fio Apple recursos aprimorados 6 horas áudio apenas 1 recarga áudio espacial cancelamento ativo ruído modo ambiente adaptável outros recursos FAST SHOP R 229573 Anunciado setembro 2022 AirPods Pro 2ª geração redesenhado melhorar experiência usuários leve 53 gramas cada fone fio adota visual arredondado hastes traz quatro pontas silicone ajustáveis Combinado driver maior amplitude acessório usa chip áudio H2 Apple Além ampla qualidade sonora modelo entrega recursos cancelamento ativo ruído ANC imersivo Modo Ambiente Áudio Espacial som 360º Cada fone traz microfones duplos filtragem especial melhorando qualidade chamadas eliminar ruídos externos mais pessoa pode atender ligações controlar reprodução comandos toque AirPods Pro 2 mantém design minimalista seguido Apple Fonte AppleDivulgação AirPods Pro 2ª Geração conexão Bluetooth 53 autonomia 6 horas reprodução música ANC habilitado Então estojo recarga garante 30 horas extras entretenimento fone fio caixa transporte têm certificação IPX4 resistência água suor sendo recomendado esportistas Vale mencionar que caso perda acessórios podem localizados app Buscar Apple Brasil AirPods Pro 2ª geração vendido preço sugerido R 2599 lojas oficiais Apple Seguindo padrão minimalista marca modelo disponível apenas cor branca Galaxy Buds 2 Pro Fone Ouvido Bluetooth Samsung Galaxy Buds 2 Pro Fone Ouvido Bluetooth Samsung Galaxy Buds 2 Pro conta desing moderno intraauricular tecnologia Bluetooth suporte assistente pessoal resistência água estojo recarga duração bateria 8 horas BUSCAPÉ R 79200 Galaxy Buds 2 Pro lançado agosto 2022 várias melhorias comparado gerações anteriores fones Samsung formato feijões leve 55 gramas cada modelo design ergonômico traz pontas silicone altofalantes bidirecionais acessório reproduzem áudio alta fidelidade 24 bits Bem como fone fio traz ANC inteligente  ajusta isolamento conforme ruídos redor  modo Som Ambiente tecnologia Dolby Atmos suporte 360 Audio Outro atrativo recurso detecção voz desabilita ANC usuário começa conversar outra pessoa Deixando ligações limpas cada fone 3 microfones filtros ruídos externos eliminam sons suaves vento Galaxy Buds 2 Pro 15 menor geração anterior Fonte SamsungDivulgação conexão Bluetooth 53 segundo marca Galaxy Buds 2 Pro oferece 5 horas reprodução áudio ANC ativo Enquanto isso caixa transporte garante 18 horas uso ouvinte fone fio traz certificação IPX7 sobrevivendo mergulhos 1 metro 30 minutos Semelhante rival caso perda acessório estojo recarga podem localizados ajuda app SmartThings Find Samsung Disponível cores branco grafite violeta Galaxy Buds 2 Pro estreou preço sugerido R 1499 Brasil Atualmente modelo pode adquirido valores torno R 1199 varejistas brasileiros AirPods Pro 2 vs Galaxy Buds 2 Pro ganha briga Embora modelos premium AirPods Pro 2ª Geração Galaxy Buds 2 Pro atingem diferentes públicos Fonte AppleSamsungReprodução AirPods Pro 2ª Geração Galaxy Buds 2 Pro têm muitos pontos comum cada produto traz várias particularidades Indiretamente fones fio premium buscam atingir diferentes públicosalvo isso necessário considerar certos pontos antes compra AirPods Pro 2 indicado usuários outros produtos Apple iPhones computadores Macs Vale citar certas funcionalidades Áudio Espacial disponíveis usar fone dispositivos outras marcas Galaxy Buds 2 Pro recomendado donos celulares Android máquinas Windows exemplo Independentemente dispositivo modelo entrega todos recursos mencionados incluindo suporte áudio alta fidelidade possível definir campeão visto cada modelo fone combina perfil usuário Entretanto nada impede usuário Apple use produto Samsung viceversa  Descobriu modelo fone Bluetooth combina estilo Fique olho TecMundo conteúdos assim", "link": "https://www.tecmundo.com.br/produto/262811-comparativo-galaxy-buds-2-pro-vs-airpods-pro-2-geracao.htm"}, {"title": "Nothing Ear 2 é lançado: fone briga com AirPods Pro com novas funções", "text": "Nothing empresa tecnologia fundada Carl Pei acaba anunciar novo lançamento fones ouvido fio Nothing Ear 2 objetivo aprimorar primeira geração fones ouvido novo produto oferece série melhorias significativas Novos fones ouvido marca Nothing Fonte NothingDivulgação Embora Ear 2 pareçam semelhantes antecessores redesenhados alguns aprimoramentos case menor utiliza menos materiais construção fones possuem formato interior ajustado acomodar todas outras mudanças lista recursos Além disso suportam LHDC 50 codec áudio garante transmissão frequência 24 bits192kHz velocidades 1Mbps significa som transmitido via Bluetooth pode ainda próximo conduzido fio Bluetooth controles Android Authority novo produto Nothing equipado Bluetooth 54 enquanto Ear 1 possuíam Bluetooth 52 Além disso modelo recente suporta conexões multiponto permite conecte fones dois dispositivos simultaneamente controles atualizados agora invés tocar hastes controlar reprodução deve apertálas mudança torna controle fácil preciso iniciar parar reprodução trocar faixa outras funções Cancelamento ruído bateria Novos fones Nothing Ear 2 contam ANC Fonte NothingDivulgação cancelamento ativo ruído ANC Ear 2 aprimorado agora eficaz bloquear som segundo marca Além disso aparelho pode adaptar formato canal auditivo cada usuário oferecendo conforto Outra novidade Modo Adaptativo pode aumentar diminuir ANC automaticamente acordo ambiente duração bateria aprimorada recurso desativo possível obter 63 horas reprodução novo produto avanço relação longevidade anunciada Ear 1 seis horas função desligada case totalmente carregada possível chegar 36 horas reprodução antes ficar bateria fones ouvido Ear 2 podem adquiridos site oficial Nothing US 149 cerca R 780 conversão direta enquanto disponíveis apenas cor branca Acreditase modelo preto lançado eventualmente empresa fez nenhum comentário respeito disso", "link": "https://www.tecmundo.com.br/produto/262087-nothing-ear-2-lancado-fone-briga-airpods-pro-com-novas-funcoes.htm"}, {"title": "5 formas de descobrir se o AirPods é original", "text": "Apple sempre marca inovadora trata tecnologia lançando série tendências replicadas mercado posteriormente mundo fonográfico diferente principais apostas empresa trazer qualidade sonora clientes AirPods fones ouvido fio marca eles possível ter 5 horas reprodução ininterrupta músicas além cancelamento ruído externo conexão Bluetooth 50 integração outros dispositivos Apple iPhones Apple Watchs Devido grande popularidade muitas cópias AirPods têm surgido mercado fazendo algumas pessoas ficarem confusas origem produto visualizado principalmente trata lojas desconhecidas Dessa maneira intuito ajudar leitores podem passando situação trouxemos matéria 5 formas descobrir AirPods original Confira abaixo 1 Valor produto UnsplashReprodução Fonte Unsplash itens Apple costumam ter valor acima média comparados produtos similares mercado Ainda preço loja oficial caro grandes nomes ecommerce seguem determinada faixa preço principais pontos prestar atenção antes realizar compra Normalmente sites anunciam AirPods preços atrativos podem falsos comercializando produto trata original sim imitação motivo recomendado realizar compra itens apenas lojas conhecidas possuem marca consolidada mercado Além disso sites estrangeiros indicamos sempre ler comentários outros consumidores saber falando produto 2 Embalagem acordo fãs Apple grandes experiências adquirir produtos marca retirálos embalagem porque empresa costuma utilizar bons materiais construção embalagem além pensar apresentação produto dentro motivo outra forma saber fones adquiridos originais observando embalagem vendidos acaso transparecer frágil apresentar logotipos cores fogem tradicional certamente trata cópia Algumas características embalagens Apple brancas apresentam foto produto tampa superior enquanto laterais possuem nome descrição item 3 Estrutura fones UnsplashReprodução Fonte Unsplash dicas anteriores suficientes identificar AirPods verdadeiro prestar atenção estrutura produto pode solucionar questão Tanto case carregamento próprios fones materiais utilizados Apple considerados boa qualidade especialistas garante item bom acabamento final Indo contrário disso falsificações costumam parecer frágeis podem tão confortáveis versão original cor branca fones pode opaca nesses produtos diferente brilho modelos AirPods costumam ter Além disso funcionalidade interessante fones Apple emparelhados forma automática outros itens marcas iPhones Sendo assim caso ocorra chances produto falso podem grandes 4 Qualidade sonora Prestar atenção qualidade sonora AirPods pode forma descobrir verdadeiros Recursos equalização adaptativa drivers dinâmicos outras tecnologias presentes modelo original elevar experiência usuários isso perceber músicas sendo reproduzidas boa qualidade apresentarem algum tipo chiado pode tratarse cópia 5 Número série PexelsReprodução Fonte Pexels última forma descobrir AirPods original partir número série presente todos dispositivos Apple informação pode encontrada tanto fones parte baixo cada deles ajustes iPhone AirPods conectado dispositivo vez informação encontrada usuários maçã devem utilizar ferramenta Check Coverage empresa verificar autenticidade produto acessála basta clicar aqui seguida preciso inserir número série visualizado aguardar ver reconhecido Apple caso negativa quer dizer produto adquirido original Compre AirPods Original Confira algumas opções originais fone fio Apple Fone Ouvido Bluetooth Apple Airpods 2 35 OFF Fone Ouvido Bluetooth Apple Airpods 2 som qualidade premiada Apple Airpods 2 configura apenas 1 toque Além saber ouvido possui carregamento fio ligam desligam automaticamente R 164900 AMAZON R 107910 Fone Ouvido Bluetooth Apple Airpods 3 Fone Ouvido Bluetooth Apple Airpods 3 Conheça todas novidades AirPods áudio espacial escutar som todos lados equalização adaptativa ajusta música ouvidos bateria maior duração resistência suor água Prontos levar experiência mágica BUSCAPÉ R 159999 Fone Ouvido Bluetooth Apple Airpods Pro Fone Ouvido Bluetooth Apple AirPods Pro Fone Ouvido Bluetooth Airpod Pro Apple conta microfone cancelamento ruído resistente água suor conta suporte assistente pessoal estojo carregamento gerenciamento chamadas BUSCAPÉ R 152910", "link": "https://www.tecmundo.com.br/produto/259324-5-formas-descobrir-airpods-original.htm"}, {"title": "AirPods Lite 'baratinho' deve ser lançado em 2024 ou 2025", "text": "Suposta versão barata fone ouvido Apple AirPods Lite deve chegar lojas final 2024 início 2025 conforme especulou analista MingChi Kuo nesta quintafeira 12 fabricante estaria pensando modelo preço acessível competir concorrência Conforme especialista assuntos Maçã big tech pode estrear versão baratinha fone segundo semestre próximo ano juntamente aguardada atualização AirPods Max chegou lojas 2020 entanto lançamento variante entrada descartado primeiro semestre 2025 AirPods 2 vs AirPods 3 diferenças impactantes relação preço AirPods Lite Kuo diz deverá custar US 99 valor equivalente R 508 cotação hoje considerar taxas impostos significaria redução US 30 R 153 comparado modelo acessível segunda geração fone vendido gigante Cupertino 45 The nextgeneration AirPods will likely begin mass shipments in 2H24 or 1H25 including more affordable AirPods with Apple targeting price of 99 and new AirPods Max which will be assembled by Luxshare ICT and Hon Teng   MingChi Kuo mingchikuo January 12 2023 Brasil modelo barato venda atualmente preço sugerido Apple R 1399 valor referente AirPods 2ª geração variante básica versão Pro mesma geração sai R 2599 enquanto AirPods 3ª geração custa R 1899 AirPods Max vendido R 6590 Ficha técnica indefinida Detalhes sobre especificações novo AirPods barato ainda divulgados esperar ausências alguns recursos garantir preço acessível Especulase modelo suporte Áudio Espacial recarga fio exemplo Vale destacar que momento Apple confirmou produção desta versão embora Kuo outras fontes confiáveis venham falando sobre modelo algum tempo Fone Ouvido Apple AirPods Pro 2ª Geração fone ouvido fio Apple recursos aprimorados 6 horas áudio apenas 1 recarga áudio espacial cancelamento ativo ruído modo ambiente adaptável outros recursos BUSCAPÉ R 152910", "link": "https://www.tecmundo.com.br/produto/259128-airpods-lite-baratinho-deve-lancado-2024-2025.htm"}, {"title": "AirPods Lite: Apple pode lançar versão baratinha de seu fone", "text": "Famosa linha fones ouvido fio Apple AirPods pode ganhar versão preço acessível menos indica analista Jeff Pu fonte confiável assuntos indústria eletrônicos Batizado AirPods Lite acessório pode estrear valores abaixo US 129 cerca R 1080 atual conversão direta Contudo produto ainda ficaria categoria acima AirPods 2ª geração preço reduzido US 99 R 537 AirPods Lite assumiria posto opção intermediária AirPods 2ª geração Fonte AppleDivulgação Segundo Jeff Pu devido baixa procura fones ouvido remessas AirPods pode ter queda 13 2023 analista sugere redução 73 milhões unidades 2022 63 milhões unidades neste ano mais especialista revela lançamento AirPods 3ª geração resposta suave mercado dado reforça previsão baixas vendas acessórios 2023 Itaú agora vende AirPods programa iPhone pra Sempre Contudo Jeff Pu diz Apple deve lançar suposto AirPods Lite outra variante fones ouvido neste ano Bem como detalhes técnicos sobre opção baixo custo acessório diversos mercados AirPods 2ª geração fone ouvido barato Apple Fonte AppleDivulgação Preços AirPods Atualmente linha AirPods Apple quatro modelos AirPods Pro 2ª geração AirPods 3ª geração AirPods 2ª geração AirPods Max Brasil fones ouvido podem adquiridos preços partir R 1399 Apple Brasil AirPods Pro 2 caro mundo suposta chegada AirPods Lite dito possível AirPods 2ª geração redução preço diversos mercados Bem como fabricante novo produto disputar espaço opções intermediárias outras marcas", "link": "https://www.tecmundo.com.br/produto/257811-airpods-lite-apple-lancar-versao-baratinha-fone.htm"}, {"title": "Itaú agora vende AirPods no programa iPhone pra Sempre", "text": "Itaú atualizou programa iPhone pra Sempre Agora além smartphones Apple usuários conseguem adquirir AirPods Podem participar programa feito parceria big tech clientes banco cartões Itaú compra deve realizada dentro aplicativo banco entrega frete grátis cliente precisa selecionar modelo AirPods deseja parcelar compra 21 vezes juros cartão crédito tanto Itaú Credicard Fone AirPods Pro 2 vs AirPods Pro 2019 veja diferenças AirPods 2ª geração custam R 1299 ficam parcelas R 6186 3ª geração fones ouvido Apple saem 21 parcelas R 11024 totalizando R 2315 fim AirPods Pro ficam R 12119 total R 2547 AirPods programa iPhone pra Sempre podem trocados devolvidos Fonte Lala AzizliUnsplash programa existe desde 2020 pagar mensalidade iPhone pra Sempre cliente pode trocar dispositivo após tempo determinado smartphone antigo deve devolvido seguindo instruções enviadas email grande diferença AirPods podem trocados devolvidos Cada pessoa pode comprar cinco dispositivos juntando fones celulares Mas preciso ter limite disponível cartão crédito modalidade seguro programa", "link": "https://www.tecmundo.com.br/dispositivos-moveis/257582-itau-vende-airpods-programa-iphone-pra-sempre.htm"}, {"title": "Como usar o AirPods Pro 2 com um celular Android?", "text": "Trazendo várias melhorias AirPods Pro 2 disponível Brasil contrário muitos usuários acreditam fones ouvido Apple podem usados dispositivos Android Neste breve guia explicaremos passo passo conectar AirPods Pro 2 outro fone Maçã smartphones Android Bem como revelamos diferenças usar fones ouvido aparelhos iPhones segunda geração AirPods Pro estreia novo conjunto driver áudio Fonte AppleDivulgação parear AirPods Pro 2 celular Android pareamento AirPods Pro 2 dispositivo Android processo semelhante conectar qualquer outro fone ouvido bluetooth Acompanhe passo passo abaixo Pressione botão parte trás estojo transporte AirPods Pro 2 alguns segundos luz indicadora piscar branco indica fone modo emparelhamento telefone Android acesse configurações Bluetooth aparelho Espere AirPods Pro 2 listado toque iniciar conexão fio alguns dispositivos pode surgir notificação solicitando permissão acesso lista contatos histórico chamadas Pronto agora possível ouvir música assistir vídeos realizar chamadas usando AirPods Pro 2 Vale mencionar procedimento serve conectar outros modelos fones bluetooth Apple smartphones Android usar AirPods Pro 2 dispositivo Android fone ouvido perde alguns recursos Fonte AppleDivulgação Quais desvantagens usar AirPods Pro 2 Android Infelizmente AirPods Pro 2 outros fones Apple perdem algumas funcionalidades serem usados telefone Android primeira pareamento rápido apenas toque abrir estojo transporte disponível somente iPhones Apple anuncia AirPods Pro 2 30h bateria ANC melhorado usuários exigentes podem sentir falta suporte Áudio Espacial função simula experiência sonora 360 graus exclusiva telefones outros dispositivos Maçã sensor detecção pele usado pausar música pessoa tira fones orelha fica desativado usado Android Bem como usuário pode personalizar comandos toque ativar modo transparência Outros modelos fones ouvido Apple AirPods Max podem usados celulares Android Fonte AppleDivulgação Vale pena usar AirPods Pro 2 dispositivo Android Usar AirPods Pro 2 outro fone ouvido Apple aparelhos Android depende perfil usuário exemplo acessórios úteis pessoas usam tanto dispositivos Maçã quanto celulares sistema operacional móvel Google outro lado produto traz tantos benefícios consumidor usa apenas celulares tablets Android tempo integral Ainda considerar ausência diversos recursos exclusivos iPhones Apple Brasil AirPods Pro 2 caro mundo Nesse último cenário recomendação procurar fone ouvido bluetooth converse Android entregue funcionalidades semelhantes mais acessórios podem ter preços acessíveis modelos Apple sabia conectar AirPods Pro 2 telefones Android esqueça compartilhar guia outras pessoas ainda possuem dúvida", "link": "https://www.tecmundo.com.br/produto/253882-usar-airpods-pro-2-celular-android.htm"}, {"title": "Fone Airpods Pro 2 vs Airpods Pro (2019): veja as diferenças", "text": "últimos anos fone fio modelo true wireless ganhou destaque categoria áudio Airpods Pro produtos cobiçados consumidores aficionados boa qualidade sonora ano Apple lançou 2ª geração AirPods Pro vendas iniciadas recentemente recentemente novo modelo muitas diferenças anterior Nesse comparativo colocamos dois fones lado lado mostramos principais características Design gostava design primeiro Airpods Pro novo modelo praticamente mantém visual vem consagrando Maçã diferenças bem sutis adição controles touch hates Antes possível pausar reproduzir sons pular faixas agora usuário pode deslizar dedo cima baixo aumentar diminuir volume Airpods Pro 2019 preto vs Airpods Pro 2 branco Fonte Applereprodução construção mantém padrão alumínio reafirmando status topo linha Airpods Pro Outra mudança deve tão notada respeito borrachinhas ponta fones dessa vez chegam tamanho extra maior encaixar ouvidos largos iPhone 15 Pro pode lançado botões físicos USBC estojo carregamento mantém tamanho formato assim continua conector tipo Lightning carregamento pode desapontar esperavam porta USB TipoC Além disso parte traseira case ainda conta algumas saídas sonoras auxiliar localização conjunto através sistema Busca Precisa integrado iPhone Qualidade sonora fone Airpods Pro 2 qualidade sonora superior comparado antecessor principal motivo disso inserção chip H2 traz melhorias som tridimensional recurso Equalização Adaptativa ajusta música forma inteligente gerar agudos graves bem acentuados Appledivulgação primeiro Airpods Pro Apple utilizava chip H1 trouxe boa revolução aparelhos mas antigo consequentemente inferior Somado processador 1ª geração contava dois sensores pele fones entenderam onde posicionados bolso mochila orelhas nova versão fone fio conta apenas um Recursos conectividade recurso interessante chega fone Airpods Pro 2 Áudio Espacial Personalizado função utiliza câmera True Depth iPhone escanear cabeça orelhas usuário Segundo engenheiros firmware divisão Airpods intenção fazer cada pessoa receba experiência áudio única entanto vale mencionar função chegará Airpods Pro 1 graças atualização iOS 16 lançamento novos fones agraciado conectividade Bluetooth 53 enquanto aparelho 2019 utiliza versão 50 tecnologia melhorando transmissão dados dispositivos Cancelamento ruído cancelamento ruído talvez funcionalidades fãs bom fone fio aguardado testar novos aparelhos primeiro Airdpods Pro fazia bom trabalho nesse quesito devido melhorias processador novo modelo experiência parece ainda melhor agora Appledivulgação Apple prometendo 2x performance ANC escutar músicas falar chamada Inteligência Artificial processador capaz separar barulhos indesejados sons pássaros ruídos carros conversas paralelas pessoas redor etc proporcionando melhor qualidade usuário Bateria fim bateria novo fone Airpods ganhou incremento bemvindo Agora autonomia energética gadget 6 horas reprodução direta 30 horas estojo carregamento modelo anterior possível utilizar fone 4 5 horas 24 horas case Preço disponibilidade Airpods Pro 2 disponível forma oficial Brasil custando R 2599 site Apple Airpods Pro original vez encontrado site Maçã porém pode adquirido varejistas cerca R 1750 melhor Fone Ouvido Apple AirPods Pro Airpod Pro Apple conta microfone cancelamento ruído resistente água suor conta suporte assistente pessoal estojo carregamento gerenciamento chamadas TECMUNDO COMPARADOR R 149900 Fone Ouvido Apple AirPods Pro 2ª Geração fone ouvido fio Apple recursos aprimorados 6 horas áudio apenas 1 recarga áudio espacial cancelamento ativo ruído modo ambiente adaptável outros recursos BUSCAPÉ R 152910 fone Airpods 2ª geração ganha praticamente todos aspectos comparado primeiro modelo entanto diferença preço praticamente 1000 reais modelos grande impeditivo muitos investindo modelo 2019 usuário qualidade sonora cancelamento ruído integração iPhone problemas definitivamente fone fio acima média Agora dinheiro empecilho nova versão melhores opções disponíveis mercado", "link": "https://www.tecmundo.com.br/produto/253645-fone-airpods-pro-2-vs-airpods-pro-2019-veja-diferencas.htm"}, {"title": "AirPods Max: ANC é afetado após atualização de software", "text": "atualização software lançada recentemente Apple AirPods Max parece ter afetado funcionamento cancelamento ruído ativo ANC fone ouvido reduzindo eficácia recurso problema detectado testes feitos site RTings sábado 22 após reclamações usuários mudanças ferramenta isolamento ruídos headphone fio Maçã surgido atualização firmware 4E71 nova versão ANC bloqueia pouco menos ruído faixa médios graves firmware anterior acordo publicação relatório cita ainda modificações podem notadas sons gerados motores veículos aviões viagens trem barulhos ficaram audíveis update proprietário funcionalidade ativada ANC AirPods Max continua ótimo geral acordo relatório Fonte AppleDivulgação documento responsáveis testes ANC Apple AirPods Max mencionam percepção ruídos varia usuário outro seja enquanto alguns poderão notar ruídos maneira evidente outros sequer perceberão tais sons comentaram ainda cancelamento segue funcionando extremamente bem demais frequências Update automático lembra XDA atualizações software AirPods realizadas automaticamente segundo plano isso usuário possa fazer bloqueálas maneira oficial reverter consequências Apesar reclamações surgidas principalmente fóruns online Apple ainda pronunciou sobre mudança ANC AirPods Max ficando claro disponibilizará novo update corrigir problema", "link": "https://www.tecmundo.com.br/produto/253293-airpods-max-anc-afetado-atualizacao-software.htm"}]